PyInstallerEx/PyInstallerEx.py
PyInstallerEx/__init__.py
PyInstallerEx/__main__.py
PyInstallerEx/core/__init__.py
PyInstallerEx/core/config.py
PyInstallerEx/core/packager.py
PyInstallerEx/utils/__init__.py
PyInstallerEx/utils/compression.py
PyInstallerEx/utils/file_utils.py
PyInstallerEx/utils/logging.py
PyInstallerEx/utils/system_utils.py
pyinstallerex-0.1.6.dist-info/LICENSE
pyinstallerex-0.1.6.dist-info/METADATA
pyinstallerex-0.1.6.dist-info/WHEEL
pyinstallerex-0.1.6.dist-info/entry_points.txt
pyinstallerex-0.1.6.dist-info/top_level.txt
pyinstallerex-0.1.6.dist-info/RECORD
