Metadata-Version: 2.1
Name: pyinstallerex
Version: 0.1.6
Summary: 扩展PyInstaller 使其拥有单文件安装功能 不用每次都解压执行
Home-page: https://gitee.com/iiixxxiii/py-installer-ex
Author: lixin
Author-email: iiixxxiii@qq.com
License: MIT
Keywords: PyInstaller,expand,single-file,installer
Platform: UNKNOWN
Classifier: Development Status :: 4 - Beta
Classifier: Environment :: Console
Classifier: Intended Audience :: Developers
Classifier: Programming Language :: Python :: 2.7
Classifier: Programming Language :: Python :: 3
Classifier: Programming Language :: Python :: 3.4
Classifier: Programming Language :: Python :: 3.5
Classifier: Programming Language :: Python :: 3.6
Classifier: Programming Language :: Python :: 3.7
Classifier: Programming Language :: Python :: 3.8
Classifier: Programming Language :: Python :: 3.9
Classifier: Programming Language :: Python :: 3.10
Classifier: Programming Language :: Python :: 3.11
Classifier: License :: OSI Approved :: MIT License
Classifier: Operating System :: OS Independent
Classifier: Topic :: Software Development :: Build Tools
Requires-Python: >=2.7, !=3.0.*, !=3.1.*, !=3.2.*, !=3.3.*
Requires-Dist: PyInstaller (>=3.2.1)
